timon/__init__.py
timon/bld_commands.py
timon/commands.py
timon/configure.py
timon/init.py
timon/resources.py
timon/run.py
timon/runner.py
timon/state.py
timon/conf/__init__.py
timon/conf/config.py
timon/conf/flags.py
timon/conf/grpby.py
timon/conf/settings.py
timon/data/examples/timon.yaml
timon/data/scripts/timonloop.sh
timon/data/test/cfg0.json
timon/data/test/cfg0.yaml
timon/data/test/cfg1.json
timon/data/test/cfg1.yaml
timon/data/test/notif0.yaml
timon/data/test/queue0.yaml
timon/db/__init__.py
timon/db/backends.py
timon/db/models.py
timon/db/peewee_utils.py
timon/db/store.py
timon/notifiers/__init__.py
timon/notifiers/base.py
timon/notifiers/cmd.py
timon/notifiers/postrequest.py
timon/plugins/__init__.py
timon/plugins/base.py
timon/plugins/timon_httpsrv.py
timon/plugins/http_server/__init__.py
timon/plugins/http_server/views.py
timon/probes/__init__.py
timon/probes/probe_if.py
timon/probes/probes.py
timon/scripts/__init__.py
timon/scripts/cert_check.py
timon/scripts/clientca_check.py
timon/scripts/http_json.py
timon/scripts/isup.py
timon/testing/__init__.py
timon/testing/tst_probe.py
timon/tests/__init__.py
timon/tests/common.py
timon/tests/helpers.py
timon/tests/notifier.py
timon/tests/probe.py
timon/tests/test_config.py
timon/tests/test_crt.py
timon/tests/test_db.py
timon/tests/test_http_probe.py
timon/tests/test_notify.py
timon/tests/test_queue.py
timon/utils/__init__.py
timon/utils/report_status.py
timon/webclient/webif1/index.html
timon/webclient/webif1/dist/.gitkeep
timon-0.4.0.dist-info/LICENSE.txt
timon-0.4.0.dist-info/METADATA
timon-0.4.0.dist-info/WHEEL
timon-0.4.0.dist-info/entry_points.txt
timon-0.4.0.dist-info/top_level.txt
timon-0.4.0.dist-info/RECORD
