Metadata-Version: 2.1
Name: timon
Version: 0.4.0
Summary: simple, low resource monitoring tool
Home-page: https://www.teledomic.eu
Author: Teledomic
Author-email: info@teledomic.eu
License: Apache Software License
Project-URL: Homepage, https://github.com/feenes/timon
Project-URL: Documentation, https://github.com/feenes/timon
Project-URL: Source, https://github.com/feenes/timon
Project-URL: SayThanks, https://github.com/feenes
Project-URL: Funding, https://donate.pypi.org
Project-URL: Tracker, https://github.com/feenes/timon/issues
Keywords: tiny monitor
Classifier: Development Status :: 3 - Alpha
Requires-Python: >=3.11, <4
License-File: LICENSE.txt
Requires-Dist: click
Requires-Dist: cryptography
Requires-Dist: httpx
Requires-Dist: mytb
Requires-Dist: minibelt
Requires-Dist: peewee
Requires-Dist: pyyaml
Requires-Dist: pyopenssl
Requires-Dist: requests
Requires-Dist: quart
